Workbook

Sheet Dashboard
A1: INDIAN INVESTMENT PORTFOLIO TRACKER
A2: Last Updated | B2: 46069 | J2: Month | K2: Net Worth | L2: Income | M2: Expenses | N2: Investments | P2: Holding | Q2: Value
J3: 45901 | K3: =$B$7*0.88 | L3: =SUMIFS(TransactionHistory!$F:$F,TransactionHistory!$A:$A,">="&J3,TransactionHistory!$A:$A,"<"&EDATE(J3,1),TransactionHistory!$D:$D,"Maturity")+SUMIFS(TransactionHistory!$F:$F,TransactionHistory!$A:$A,">="&J3,TransactionHistory!$A:$A,"<"&EDATE(J3,1),TransactionHistory!$D:$D,"Sell") | M3: =SUMIFS(TransactionHistory!$F:$F,TransactionHistory!$A:$A,">="&J3,TransactionHistory!$A:$A,"<"&EDATE(J3,1),TransactionHistory!$D:$D,"Withdrawal") | N3: =SUMIFS(TransactionHistory!$F:$F,TransactionHistory!$A:$A,">="&J3,TransactionHistory!$A:$A,"<"&EDATE(J3,1),TransactionHistory!$D:$D,"Buy")+SUMIFS(TransactionHistory!$F:$F,TransactionHistory!$A:$A,">="&J3,TransactionHistory!$A:$A,"<"&EDATE(J3,1),TransactionHistory!$D:$D,"Deposit") | P3: Real Estate | Q3: =RealEstate!F11
A4: Net Worth Summary | J4: 45931 | K4: =$B$7*0.9 | L4: =SUMIFS(TransactionHistory!$F:$F,TransactionHistory!$A:$A,">="&J4,TransactionHistory!$A:$A,"<"&EDATE(J4,1),TransactionHistory!$D:$D,"Maturity")+SUMIFS(TransactionHistory!$F:$F,TransactionHistory!$A:$A,">="&J4,TransactionHistory!$A:$A,"<"&EDATE(J4,1),TransactionHistory!$D:$D,"Sell") | M4: =SUMIFS(TransactionHistory!$F:$F,TransactionHistory!$A:$A,">="&J4,TransactionHistory!$A:$A,"<"&EDATE(J4,1),TransactionHistory!$D:$D,"Withdrawal") | N4: =SUMIFS(TransactionHistory!$F:$F,TransactionHistory!$A:$A,">="&J4,TransactionHistory!$A:$A,"<"&EDATE(J4,1),TransactionHistory!$D:$D,"Buy")+SUMIFS(TransactionHistory!$F:$F,TransactionHistory!$A:$A,">="&J4,TransactionHistory!$A:$A,"<"&EDATE(J4,1),TransactionHistory!$D:$D,"Deposit") | P4: Market Investments | Q4: =MutualFunds!G21+Stocks!G21
A5: Total Assets | B5: =Banking!D11+MutualFunds!G21+Stocks!G21+Gold!G7+RealEstate!F11+Retirement!C11+Insurance!I11+OtherAssets!E11 | J5: 45962 | K5: =$B$7*0.93 | L5: =SUMIFS(TransactionHistory!$F:$F,TransactionHistory!$A:$A,">="&J5,TransactionHistory!$A:$A,"<"&EDATE(J5,1),TransactionHistory!$D:$D,"Maturity")+SUMIFS(TransactionHistory!$F:$F,TransactionHistory!$A:$A,">="&J5,TransactionHistory!$A:$A,"<"&EDATE(J5,1),TransactionHistory!$D:$D,"Sell") | M5: =SUMIFS(TransactionHistory!$F:$F,TransactionHistory!$A:$A,">="&J5,TransactionHistory!$A:$A,"<"&EDATE(J5,1),TransactionHistory!$D:$D,"Withdrawal") | N5: =SUMIFS(TransactionHistory!$F:$F,TransactionHistory!$A:$A,">="&J5,TransactionHistory!$A:$A,"<"&EDATE(J5,1),TransactionHistory!$D:$D,"Buy")+SUMIFS(TransactionHistory!$F:$F,TransactionHistory!$A:$A,">="&J5,TransactionHistory!$A:$A,"<"&EDATE(J5,1),TransactionHistory!$D:$D,"Deposit") | P5: Retirement Funds | Q5: =Retirement!C11
A6: Total Liabilities | B6: =Loans!E11 | J6: 45992 | K6: =$B$7*0.96 | L6: =SUMIFS(TransactionHistory!$F:$F,TransactionHistory!$A:$A,">="&J6,TransactionHistory!$A:$A,"<"&EDATE(J6,1),TransactionHistory!$D:$D,"Maturity")+SUMIFS(TransactionHistory!$F:$F,TransactionHistory!$A:$A,">="&J6,TransactionHistory!$A:$A,"<"&EDATE(J6,1),TransactionHistory!$D:$D,"Sell") | M6: =SUMIFS(TransactionHistory!$F:$F,TransactionHistory!$A:$A,">="&J6,TransactionHistory!$A:$A,"<"&EDATE(J6,1),TransactionHistory!$D:$D,"Withdrawal") | N6: =SUMIFS(TransactionHistory!$F:$F,TransactionHistory!$A:$A,">="&J6,TransactionHistory!$A:$A,"<"&EDATE(J6,1),TransactionHistory!$D:$D,"Buy")+SUMIFS(TransactionHistory!$F:$F,TransactionHistory!$A:$A,">="&J6,TransactionHistory!$A:$A,"<"&EDATE(J6,1),TransactionHistory!$D:$D,"Deposit") | P6: Banking & Deposits | Q6: =Banking!D11
A7: NET WORTH | B7: =B5-B6 | J7: 46023 | K7: =$B$7*0.98 | L7: =SUMIFS(TransactionHistory!$F:$F,TransactionHistory!$A:$A,">="&J7,TransactionHistory!$A:$A,"<"&EDATE(J7,1),TransactionHistory!$D:$D,"Maturity")+SUMIFS(TransactionHistory!$F:$F,TransactionHistory!$A:$A,">="&J7,TransactionHistory!$A:$A,"<"&EDATE(J7,1),TransactionHistory!$D:$D,"Sell") | M7: =SUMIFS(TransactionHistory!$F:$F,TransactionHistory!$A:$A,">="&J7,TransactionHistory!$A:$A,"<"&EDATE(J7,1),TransactionHistory!$D:$D,"Withdrawal") | N7: =SUMIFS(TransactionHistory!$F:$F,TransactionHistory!$A:$A,">="&J7,TransactionHistory!$A:$A,"<"&EDATE(J7,1),TransactionHistory!$D:$D,"Buy")+SUMIFS(TransactionHistory!$F:$F,TransactionHistory!$A:$A,">="&J7,TransactionHistory!$A:$A,"<"&EDATE(J7,1),TransactionHistory!$D:$D,"Deposit") | P7: Precious Metals | Q7: =Gold!G7
J8: 46054 | K8: =$B$7*1.0 | L8: =SUMIFS(TransactionHistory!$F:$F,TransactionHistory!$A:$A,">="&J8,TransactionHistory!$A:$A,"<"&EDATE(J8,1),TransactionHistory!$D:$D,"Maturity")+SUMIFS(TransactionHistory!$F:$F,TransactionHistory!$A:$A,">="&J8,TransactionHistory!$A:$A,"<"&EDATE(J8,1),TransactionHistory!$D:$D,"Sell") | M8: =SUMIFS(TransactionHistory!$F:$F,TransactionHistory!$A:$A,">="&J8,TransactionHistory!$A:$A,"<"&EDATE(J8,1),TransactionHistory!$D:$D,"Withdrawal") | N8: =SUMIFS(TransactionHistory!$F:$F,TransactionHistory!$A:$A,">="&J8,TransactionHistory!$A:$A,"<"&EDATE(J8,1),TransactionHistory!$D:$D,"Buy")+SUMIFS(TransactionHistory!$F:$F,TransactionHistory!$A:$A,">="&J8,TransactionHistory!$A:$A,"<"&EDATE(J8,1),TransactionHistory!$D:$D,"Deposit")
A9: Asset Allocation
A10: Category | B10: Current Value (₹) | C10: % of Total | D10: Notes
A11: Banking & Deposits | B11: =Banking!D11 | C11: =B11/$B$18*100 | D11: Primary liquid assets
A12: Market Investments | B12: =MutualFunds!G21+Stocks!G21 | C12: =B12/$B$18*100 | D12: MF + Direct Equity
A13: Precious Metals | B13: =Gold!G7 | C13: =B13/$B$18*100 | D13: Gold and silver
A14: Real Estate | B14: =RealEstate!F11 | C14: =B14/$B$18*100 | D14: Property market value
A15: Retirement Funds | B15: =Retirement!C11 | C15: =B15/$B$18*100 | D15: EPF/PPF/NPS
A16: Insurance (Cash Value) | B16: =Insurance!I11 | C16: =B16/$B$18*100 | D16: Surrender value only
A17: Other Assets | B17: =OtherAssets!E11 | C17: =B17/$B$18*100 | D17: Vehicles, crypto, ESOPs
A18: TOTAL ASSETS | B18: =SUM(B11:B17) | C18: =B18/$B$18*100
A20: Equity (Net Worth) | B20: =B7
A21: Debt (Liabilities) | B21: =Loans!E11

Sheet Banking
A1: Account Type | B1: Bank Name | C1: Account Number | D1: Current Balance (₹) | E1: Interest Rate (%) | F1: Maturity Date | G1: Remarks
A2: Savings | B2: HDFC Bank | C2: XXXX1234 | D2: 50000 | E2: 3.5 | G2: Primary Account
A3: FD | B3: SBI | C3: XXXX5678 | D3: 200000 | E3: 7.1 | F3: 46249 | G3: 5 Year FD
A4: RD | B4: ICICI | C4: XXXX9012 | D4: 50000 | E4: 6.8 | F4: 46386 | G4: Monthly ₹5000
A5: PPF | B5: SBI | C5: XXXX3456 | D5: 500000 | E5: 7.1 | F5: 51591 | G5: Annual Contribution
A11: TOTAL | D11: =SUM(D2:D10)

Sheet MutualFunds
A1: Folio Number | B1: AMC | C1: Scheme Name | D1: Category | E1: Units | F1: Current NAV | G1: Current Value (₹) | H1: Invested Amount (₹) | I1: Gain/Loss (₹) | J1: Gain/Loss (%) | K1: XIRR (%) | L1: SIP Amount (₹) | M1: SIP Date
A2: 12345/67 | B2: HDFC MF | C2: HDFC Flexi Cap | D2: Equity | E2: 1000.5 | F2: 850.25 | G2: =E2*F2 | H2: 750000 | I2: =G2-H2 | J2: =I2/H2 | K2: 15.5 | L2: 10000 | M2: 5th
A3: 23456/78 | B3: SBI MF | C3: SBI Bluechip | D3: Equity | E3: 500 | F3: 95.5 | G3: =E3*F3 | H3: 45000 | I3: =G3-H3 | J3: =I3/H3 | K3: 12.3 | L3: 5000 | M3: 10th
A21: TOTAL | G21: =SUM(G2:G20) | H21: =SUM(H2:H20) | I21: =SUM(I2:I20) | J21: =I21/H21

Sheet Stocks
A1: Stock Symbol | B1: Company Name | C1: Exchange | D1: Quantity | E1: Avg Buy Price (₹) | F1: Current Price (₹) | G1: Current Value (₹) | H1: Invested Amount (₹) | I1: Unrealized Gain/Loss (₹) | J1: Unrealized Gain/Loss (%) | K1: Demat Account
A2: RELIANCE | B2: Reliance Industries | C2: NSE | D2: 50 | E2: 2400 | F2: 2850 | G2: =D2*F2 | H2: =D2*E2 | I2: =G2-H2 | J2: =I2/H2 | K2: Zerodha
A3: TCS | B3: Tata Consultancy | C3: NSE | D3: 25 | E3: 3500 | F3: 4100 | G3: =D3*F3 | H3: =D3*E3 | I3: =G3-H3 | J3: =I3/H3 | K3: Zerodha
A21: TOTAL | G21: =SUM(G2:G20) | H21: =SUM(H2:H20) | I21: =SUM(I2:I20) | J21: =I21/H21

Sheet Gold
A1: Type | B1: Sub-Type | C1: Weight (grams) | D1: Purchase Price/gram (₹) | E1: Purchase Date | F1: Current Rate/gram (₹) | G1: Current Value (₹) | H1: Gain/Loss (₹) | I1: Location/Details
A2: Gold | B2: Physical Jewelry | C2: 50 | D2: 4500 | E2: 43831 | F2: 6500 | G2: =C2*F2 | H2: =G2-(C2*D2) | I2: Home Locker
A3: Gold | B3: Coins (24K) | C3: 20 | D3: 5200 | E3: 44788 | F3: 6500 | G3: =C3*F3 | H3: =G3-(C3*D3) | I3: Bank Locker
A4: Gold | B4: Digital Gold | C4: 10 | D4: 5500 | E4: 45301 | F4: 6500 | G4: =C4*F4 | H4: =G4-(C4*D4) | I4: Paytm
A5: Gold | B5: Sovereign Gold Bonds | C5: 16 | D5: 5000 | E5: 45017 | F5: 6500 | G5: =C5*F5 | H5: =G5-(C5*D5) | I5: Demat
A6: Silver | B6: Physical Bars | C6: 500 | D6: 65 | E6: 44348 | F6: 75 | G6: =C6*F6 | H6: =G6-(C6*D6) | I6: Home
A7: TOTAL | C7: =SUM(C2:C6) | G7: =SUM(G2:G6) | H7: =SUM(H2:H6)

Sheet RealEstate
A1: Property Type | B1: Address | C1: City | D1: Purchase Date | E1: Purchase Price (₹) | F1: Current Market Value (₹) | G1: Loan Outstanding (₹) | H1: Net Equity (₹) | I1: Rental Income (₹/month) | J1: Remarks
A2: Residential | B2: Sector 62, Noida | C2: Noida | D2: 43905 | E2: 7500000 | F2: 9500000 | G2: 3000000 | H2: =F2-G2 | I2: 25000 | J2: Self-occupied
A3: Plot | B3: Greater Noida | C3: Noida | D3: 43101 | E3: 2500000 | F3: 4000000 | G3: 0 | H3: =F3-G3 | J3: Vacant
A11: TOTAL | E11: =SUM(E2:E10) | F11: =SUM(F2:F10) | G11: =SUM(G2:G10) | H11: =SUM(H2:H10) | I11: =SUM(I2:I10)

Sheet Retirement
A1: Account Type | B1: Account Number | C1: Current Balance (₹) | D1: Employer Contribution (₹) | E1: Employee Contribution (₹) | F1: Interest Rate (%) | G1: Maturity/Retirement Date | H1: Remarks
A2: EPF | B2: PF/XX/12345 | C2: 800000 | D2: 1800/month | E2: 1800/month | F2: 8.25% | G2: 54878 | H2: Auto-deducted
A3: PPF | B3: PPF123456 | C3: 500000 | D3: - | E3: 150000/year | F3: 7.1% | G3: 51591 | H3: 15-year lock-in
A4: NPS Tier-I | B4: PRAN123456 | C4: 300000 | D4: 50000/year | E4: 50000/year | F4: Market-linked | G4: 54878 | H4: Tax benefit
A11: TOTAL | C11: =SUM(C2:C10)

Sheet Insurance
A1: Policy Type | B1: Insurer | C1: Policy Number | D1: Sum Assured (₹) | E1: Premium Amount (₹) | F1: Premium Frequency | G1: Next Due Date | H1: Maturity Date | I1: Cash/Surrender Value (₹) | J1: Nominee | K1: Status
A2: Term Life | B2: HDFC Life | C2: TERM123456 | D2: 10000000 | E2: 15000 | F2: Annual | G2: 46113 | H2: 54879 | I2: 0 | J2: Spouse | K2: Active
A3: Endowment | B3: LIC | C3: LIC987654 | D3: 1000000 | E3: 50000 | F3: Annual | G3: 46157 | H3: 49444 | I3: 350000 | J3: Spouse | K3: Active
A4: Health | B4: Star Health | C4: HEALTH5678 | D4: 1000000 | E4: 18000 | F4: Annual | G4: 46183 | H4: Annual renewal | I4: 0 | J4: Self | K4: Active
A5: Vehicle | B5: ICICI Lombard | C5: VEH123 | D5: 800000 | E5: 12000 | F5: Annual | G5: 46223 | H5: Annual renewal | I5: 0 | J5: Self | K5: Active
A11: TOTAL | D11: =SUM(D2:D10) | E11: =SUM(E2:E10) | I11: =SUM(I2:I10)

Sheet Loans
A1: Loan Type | B1: Lender | C1: Loan Account | D1: Original Amount (₹) | E1: Outstanding Amount (₹) | F1: Interest Rate (%) | G1: EMI Amount (₹) | H1: EMI Date | I1: Tenure Remaining | J1: End Date
A2: Home Loan | B2: HDFC Bank | C2: HL123456 | D2: 5000000 | E2: 3000000 | F2: 8.5 | G2: 45000 | H2: 5th | I2: 120 months | J2: 49710
A3: Car Loan | B3: ICICI Bank | C3: CL789012 | D3: 800000 | E3: 350000 | F3: 9.2 | G3: 18000 | H3: 10th | I3: 24 months | J3: 46793
A4: Personal Loan | B4: SBI | C4: PL345678 | D4: 200000 | E4: 120000 | F4: 11.5 | G4: 12000 | H4: 15th | I4: 12 months | J4: 46433
A11: TOTAL | D11: =SUM(D2:D10) | E11: =SUM(E2:E10) | G11: =SUM(G2:G10)

Sheet OtherAssets
A1: Asset Type | B1: Description | C1: Purchase Date | D1: Purchase Value (₹) | E1: Current Value (₹) | F1: Depreciation Rate (%) | G1: Remarks
A2: Vehicle | B2: Honda City 2022 | C2: 44576 | D2: 1200000 | E2: 800000 | F2: 15%/year | G2: Registration: DL-XX-XXXX
A3: Cryptocurrency | B3: Bitcoin | C3: Various | D3: 100000 | E3: 150000 | F3: Volatile | G3: WazirX account
A4: ESOPs | B4: Company Stock | C4: 45292 | D4: 200000 | E4: 300000 | F4: - | G4: Vested: 50%
A11: TOTAL | D11: =SUM(D2:D10) | E11: =SUM(E2:E10)

Sheet TransactionHistory
A1: Date | B1: Category | C1: Sub-Category | D1: Transaction Type | E1: Asset Name | F1: Amount (₹) | G1: Units/Quantity | H1: Price | I1: Account/Folio | J1: Remarks
A2: 46054 | B2: Mutual Funds | C2: Equity | D2: Buy | E2: HDFC Flexi Cap | F2: 10000 | G2: 11.75 | H2: 851.06 | I2: 12345/67 | J2: SIP
A3: 46058 | B3: Banking | C3: FD | D3: Maturity | E3: SBI FD | F3: 210500 | G3: - | H3: - | I3: XXXX5678 | J3: Reinvested
A4: 46063 | B4: Gold | C4: Physical | D4: Buy | E4: 24K Coin | F4: 55000 | G4: 10 | H4: 5500 | I4: Bank Locker | J4: -

Sheet Reminders
A1: Due Date | B1: Category | C1: Description | D1: Amount (₹) | E1: Status | F1: Alert Days Before
A2: 46113 | B2: Insurance | C2: HDFC Term Premium | D2: 15000 | E2: Pending | F2: 15
A3: 46117 | B3: Investment | C3: PPF Contribution | D3: 150000 | E3: Pending | F3: 30
A4: 46249 | B4: Banking | C4: SBI FD Maturity | D4: 200000 | E4: Pending | F4: 30

Sheet Settings
A1: CURRENT MARKET RATES
A2: Gold (24K) per gram | B2: 6500
A3: Gold (22K) per gram | B3: 5950
A4: Silver per gram | B4: 75
A5: USD to INR | B5: 83.5
A6: Last Updated | B6: 46069
A9: PERSONAL SETTINGS
A10: Financial Year | B10: 2025-26
A11: Risk Profile | B11: Moderate
A12: Target Net Worth | B12: 20000000
A13: Target Date | B13: 47848

Sheet Instructions
A1: INDIAN INVESTMENT PORTFOLIO TRACKER - USER GUIDE GETTING STARTED: 1. Start by filling in your actual data in each category sheet 2. The Dashboard will automatically calculate your total net worth 3. Update the Settings sheet with current market rates IMPORTANT FORMULAS: • Dashboard formulas automatically pull data from all other sheets • Do NOT delete the TOTAL rows - they contain important formulas • Current Value columns use formulas like =Units*Price UPDATING DATA: • Banking: Update balances monthly • Mutual Funds: Update NAV weekly or use live data • Stocks: Update prices daily or use GOOGLEFINANCE function • Gold/Silver: Update current rates from Settings sheet • Real Estate: Update valuations annually GOOGLE SHEETS ENHANCEMENTS: After uploading to Google Sheets, add: • =GOOGLEFINANCE("NSE:RELIANCE","price") for live stock prices • =GOOGLEFINANCE("CURRENCY:XAUINR")/31.1035 for live gold rates • Data validation dropdowns for consistent data entry • Conditional formatting to highlight gains/losses • Charts for visual representation MONTHLY REVIEW CHECKLIST: ☐ Update all bank account balances ☐ Update mutual fund NAVs ☐ Update stock prices ☐ Update gold/silver rates ☐ Add new transactions to Transaction History ☐ Check Reminders for upcoming payments ☐ Review Dashboard for overall net worth TIPS: • Keep documents in a secure location • Set calendar reminders for payments • Review asset allocation quarterly • Backup this file regularly PRIVACY & SECURITY: • This file contains sensitive financial information • Store it securely and password-protect if sharing • Do not share account numbers or passwords
